examples/__init__.py
examples/context.py
examples/singlephase/__init__.py
examples/singlephase/context.py
examples/singlephase/dae_vdp.py
examples/singlephase/hyper_sensitive.py
examples/singlephase/mine_opt_wiki.py
examples/singlephase/moon_lander.py
examples/singlephase/ocp_with_solution.py
examples/singlephase/robot_arm.py
examples/singlephase/Betts/__init__.py
examples/singlephase/Betts/alpr01_alp_rider.py
examples/singlephase/Betts/context.py
mpopt/__init__.py
mpopt/mpopt.py
tests/__init__.py
tests/context.py
tests/test_examples.py
tests/test_mpopt.py
mpopt-1.0.2.dist-info/LICENSE
mpopt-1.0.2.dist-info/METADATA
mpopt-1.0.2.dist-info/WHEEL
mpopt-1.0.2.dist-info/top_level.txt
mpopt-1.0.2.dist-info/RECORD
