Metadata-Version: 2.1
Name: mpopt
Version: 1.0.2
Summary: A Multi-phase nonlinear Optimal control problem solver using Pseudo-spectral collocation
Home-page: https://github.com/mpopt
Author: Devakumar THAMMISETTY, Colin Jones
Author-email: deva.aerospace@gmail.com
Project-URL: Docmentation, https://mpopt.readthedocs.io/
Project-URL: Source, https://github.com/mpopt/mpopt/
Project-URL: Tracker, https://github.com/mpopt/mpopt/issues
Keywords: optimal control,multi-phase OCP,collocation,adaptive grid refinement,nonlinear optimization
Classifier: Programming Language :: Python :: 3.12
Classifier: License :: OSI Approved :: GNU Lesser General Public License v3 (LGPLv3)
Requires-Python: >=3.12
License-File: LICENSE
Requires-Dist: wheel >=0.34
Requires-Dist: numpy ==2.0.0
Requires-Dist: typing >=3.7
Requires-Dist: casadi >=3.6.5
Requires-Dist: matplotlib >=3.9.0
Requires-Dist: scipy >=1.13.1
